odoo/addons/website_event_sale_cart_quantity_readonly/README.rst
odoo/addons/website_event_sale_cart_quantity_readonly/__init__.py
odoo/addons/website_event_sale_cart_quantity_readonly/__manifest__.py
odoo/addons/website_event_sale_cart_quantity_readonly/i18n/it.po
odoo/addons/website_event_sale_cart_quantity_readonly/i18n/website_event_sale_cart_quantity_readonly.pot
odoo/addons/website_event_sale_cart_quantity_readonly/readme/CONTRIBUTORS.rst
odoo/addons/website_event_sale_cart_quantity_readonly/readme/DESCRIPTION.rst
odoo/addons/website_event_sale_cart_quantity_readonly/static/description/icon.png
odoo/addons/website_event_sale_cart_quantity_readonly/static/description/index.html
odoo/addons/website_event_sale_cart_quantity_readonly/templates/cart.xml
odoo_addon_website_event_sale_cart_quantity_readonly-16.0.1.0.0.5.dist-info/METADATA
odoo_addon_website_event_sale_cart_quantity_readonly-16.0.1.0.0.5.dist-info/WHEEL
odoo_addon_website_event_sale_cart_quantity_readonly-16.0.1.0.0.5.dist-info/top_level.txt
odoo_addon_website_event_sale_cart_quantity_readonly-16.0.1.0.0.5.dist-info/RECORD
